{
  "name": "Arcane Mods",
  "description": "Source of awesome mods created by Aeliux.",
  "plugins_base_url": "https://github.com/Aeliux/arcane/{content_type}/{tag}/plugins",
  "plugins": {
    "open_actor": {
      "description": "A Library for injecting tasks to actor objects like Bomb and Powerups.",
      "external_url": "",
      "authors": [
        {
          "name": "Aeliux",
          "email": "itsaeliux@gmail.com"
        }
      ],
      "versions": {
        "1.2.0": null,
        "1.1.1": {
          "api_version": 8,
          "commit_sha": "362056c",
          "released_on": "03-07-2023",
          "md5sum": "7d30b65d5950ea7c7c4a94d06d758486"
        },
        "1.1.0": {
          "api_version": 8,
          "commit_sha": "6ec6b82",
          "released_on": "03-07-2023",
          "md5sum": "26fa2d19925f425f0671d36d5eefb9ce"
        },
        "1.0.2": {
          "api_version": 8,
          "commit_sha": "bec0468",
          "released_on": "03-07-2023",
          "md5sum": "35634b6c021982d8100fd8ea2d8a9dd7"
        },
        "1.0.1": {
          "api_version": 8,
          "commit_sha": "63d0937",
          "released_on": "02-07-2023",
          "md5sum": "dd2d163677ba15dbdaba287df200707e"
        },
        "1.0.0": {
          "api_version": 8,
          "commit_sha": "87b30e1",
          "released_on": "02-07-2023",
          "md5sum": "637ea32c6983db2e5ef491099e85d141"
        }
      }
    },
    "better_fight": {
      "description": "Change the feeling of fights with additional features. This mod needs open actor.",
      "external_url": "",
      "authors": [
        {
          "name": "Aeliux",
          "email": "itsaeliux@gmail.com"
        }
      ],
      "versions": {
        "1.2.2": {
          "api_version": 8,
          "commit_sha": "d0e4829",
          "released_on": "03-07-2023",
          "md5sum": "03098deac5f6b2032a331e58f50734ae"
        },
        "1.2.1": {
          "api_version": 8,
          "commit_sha": "1f32a14",
          "released_on": "03-07-2023",
          "md5sum": "51273ebaa137ff99766e0f83d805aafb"
        },
        "1.2.0": {
          "api_version": 8,
          "commit_sha": "2080ce0",
          "released_on": "03-07-2023",
          "md5sum": "467f107d7669a87758d48592a7f77f55"
        },
        "1.1.1": {
          "api_version": 8,
          "commit_sha": "4df9f16",
          "released_on": "03-07-2023",
          "md5sum": "52a7ee7431540c9edea23ffe72f1e86e"
        },
        "1.1.0": {
          "api_version": 8,
          "commit_sha": "ec1a913",
          "released_on": "02-07-2023",
          "md5sum": "9420f5fbc5182a6135519493d0f9a9b8"
        },
        "1.0.0": {
          "api_version": 8,
          "commit_sha": "14401d8",
          "released_on": "02-07-2023",
          "md5sum": "a401766d11578662129ec684c731bf81"
        }
      }
    },
    "unlocker": {
      "description": "Unlocks BombSquad Pro options.",
      "external_url": "",
      "authors": [
        {
          "name": "Aeliux",
          "email": "itsaeliux@gmail.com"
        }
      ],
      "versions": {
        "1.0.0": {
          "api_version": 8,
          "commit_sha": "2e394a9",
          "released_on": "03-07-2023",
          "md5sum": "a63c85d0fc3ba44c85d3881bd774ec7a"
        }
      }
    },
    "colorful": {
      "description": "Change feeling of your game by making game elements more colorful!",
      "external_url": "",
      "authors": [
        {
          "name": "Aeliux",
          "email": "itsaeliux@gmail.com"
        }
      ],
      "versions": {
        "1.0.0": null
      }
    }
  }
}